libretranslate_neon_plugin/__init__.py
libretranslate_neon_plugin/constants/__init__.py
libretranslate_neon_plugin/constants/url_constants.py
neon_lang_plugin_libretranslate-0.2.1.dist-info/LICENSE.md
neon_lang_plugin_libretranslate-0.2.1.dist-info/METADATA
neon_lang_plugin_libretranslate-0.2.1.dist-info/WHEEL
neon_lang_plugin_libretranslate-0.2.1.dist-info/entry_points.txt
neon_lang_plugin_libretranslate-0.2.1.dist-info/top_level.txt
neon_lang_plugin_libretranslate-0.2.1.dist-info/zip-safe
neon_lang_plugin_libretranslate-0.2.1.dist-info/RECORD
