Metadata-Version: 2.1
Name: neon-lang-plugin-libretranslate
Version: 0.2.1
Home-page: 
Author: Neongecko
Author-email: developers@neon.ai
License: BSD-3-Clause
Keywords: neon mycroft plugin language detection translation
Classifier: Development Status :: 3 - Alpha
Classifier: Intended Audience :: Developers
Classifier: Topic :: Text Processing :: Linguistic
Classifier: License :: OSI Approved :: Apache Software License
Classifier: Programming Language :: Python :: 2
Classifier: Programming Language :: Python :: 2.7
Classifier: Programming Language :: Python :: 3
Classifier: Programming Language :: Python :: 3.0
Classifier: Programming Language :: Python :: 3.1
Classifier: Programming Language :: Python :: 3.2
Classifier: Programming Language :: Python :: 3.3
Classifier: Programming Language :: Python :: 3.4
Classifier: Programming Language :: Python :: 3.5
Classifier: Programming Language :: Python :: 3.6
License-File: LICENSE.md
Requires-Dist: ovos-plugin-manager>=0.0.18,~=0.0
Requires-Dist: requests
